{
  "main": {
    "id": "b3dd293e1e923fb3",
    "type": "split",
    "children": [
      {
        "id": "bd7c7d1e29d7da9b",
        "type": "tabs",
        "children": [
          {
            "id": "a35a3116117bca00",
            "type": "leaf",
            "state": {
              "type": "canvas",
              "state": {
                "file": "Places/Unknown/Unknown.canvas",
                "viewState": {
                  "x": 0,
                  "y": 0,
                  "zoom": 0
                }
              },
              "icon": "lucide-layout-dashboard",
              "title": "Unknown"
            }
          }
        ]
      }
    ],
    "direction": "vertical"
  },
  "left": {
    "id": "bdd1fd3e95e72a84",
    "type": "split",
    "children": [
      {
        "id": "b857b6536d308d62",
        "type": "tabs",
        "children": [
          {
            "id": "41cea2f8f4e38194",
            "type": "leaf",
            "state": {
              "type": "file-explorer",
              "state": {
                "sortOrder": "alphabetical",
                "autoReveal": false
              },
              "icon": "lucide-folder-closed",
              "title": "Explorador de arquivos"
            }
          },
          {
            "id": "cf34573e54fdd423",
            "type": "leaf",
            "state": {
              "type": "search",
              "state": {
                "query": "",
                "matchingCase": false,
                "explainSearch": false,
                "collapseAll": false,
                "extraContext": false,
                "sortOrder": "alphabetical"
              },
              "icon": "lucide-search",
              "title": "Search"
            }
          },
          {
            "id": "6180dce45e9e68ad",
            "type": "leaf",
            "state": {
              "type": "bookmarks",
              "state": {},
              "icon": "lucide-bookmark",
              "title": "Bookmarks"
            }
          }
        ]
      }
    ],
    "direction": "horizontal",
    "width": 300
  },
  "right": {
    "id": "80ecc5f6d5d98419",
    "type": "split",
    "children": [
      {
        "id": "2a4c87912b45d209",
        "type": "tabs",
        "children": [
          {
            "id": "81f04f10d7559763",
            "type": "leaf",
            "state": {
              "type": "backlink",
              "state": {
                "collapseAll": false,
                "extraContext": false,
                "sortOrder": "alphabetical",
                "showSearch": false,
                "searchQuery": "",
                "backlinkCollapsed": false,
                "unlinkedCollapsed": true
              },
              "icon": "links-coming-in",
              "title": "Backlinks"
            }
          },
          {
            "id": "814f5acadb045eed",
            "type": "leaf",
            "state": {
              "type": "outgoing-link",
              "state": {
                "linksCollapsed": false,
                "unlinkedCollapsed": true
              },
              "icon": "links-going-out",
              "title": "Outgoing links"
            }
          },
          {
            "id": "5c6560873b86723e",
            "type": "leaf",
            "state": {
              "type": "tag",
              "state": {
                "sortOrder": "frequency",
                "useHierarchy": true,
                "showSearch": false,
                "searchQuery": ""
              },
              "icon": "lucide-tags",
              "title": "Tags"
            }
          },
          {
            "id": "fed90a7836e90a77",
            "type": "leaf",
            "state": {
              "type": "outline",
              "state": {
                "followCursor": false,
                "showSearch": false,
                "searchQuery": ""
              },
              "icon": "lucide-list",
              "title": "Outline"
            }
          },
          {
            "id": "b66a47c1840411d8",
            "type": "leaf",
            "state": {
              "type": "git-history-view",
              "state": {},
              "icon": "history",
              "title": "History"
            }
          }
        ],
        "currentTab": 4
      }
    ],
    "direction": "horizontal",
    "width": 300
  },
  "left-ribbon": {
    "hiddenItems": {
      "switcher:Abrir a troca rápida": false,
      "graph:Abrir visualização em gráfico": false,
      "canvas:Criar novo canvas": false,
      "daily-notes:Abrir a nota de hoje": false,
      "templates:Inserir modelo": false,
      "command-palette:Abrir paleta de comandos": false,
      "obsidian-git:Open Git source control": false
    }
  },
  "active": "a35a3116117bca00",
  "lastOpenFiles": [
    "Characters/Rust/Rust.canvas",
    "Characters/Rust/Rust Reference 2.png",
    "Characters/Rust/Manto do Mestre 2.png",
    "Characters/Rust/Outfit 2 Rust.png",
    "auverse_vault",
    "Characters/Rust/Outfit Rust 1.png",
    "Elements/Cinzas/Lore & Funcionamento.md",
    "Elements/Calor dos Sete Sufocamentos/Lore & Funcionamento.md",
    "Elements/Calor dos Sete Sufocamentos/Calor dos Sete Sufocamentos Reference Gif.gif",
    "Elements/Cinzas",
    "conflict-files-obsidian-git.md",
    "Elements/Calor dos Sete Sufocamentos",
    "Elements",
    "Characters/Mujika/Mujika Apperance Reference 1.png",
    "Characters/Mujika/Mujika.canvas",
    "Characters/Mujika",
    "Characters/Lohan/Lohan Apperance Reference 1.png",
    "Characters/Lilith/Lilith Apperance Reference 1.png",
    "Characters/Haven/Haven Apperance Reference 1.png",
    "Characters/Haven/Haven.canvas",
    "Characters/Haven",
    "Characters/Fern 2/Fern 2 Apperance Reference 2.png",
    "Characters/Fern 2/Fern 2.canvas",
    "Places/Vale dos Corvos/Culture.md",
    "Places/Vale dos Corvos/Vale dos Corvos.canvas",
    "Places/Vale dos Corvos",
    "Characters/Ren 187/Ren 187.canvas",
    "Rad.md",
    "Factions/Chroma 9/Chroma 9.canvas",
    "Factions/Chroma 9",
    "Characters/Fem/Fem.canvas",
    "Characters/Fem",
    "Characters/Enyo/Enyo.canvas",
    "Characters/Enyo",
    "mandamentos.md",
    "Characters/Vaius 2/Vaius 2.canvas",
    "Characters/Fern 2/Carisma.md",
    "Characters/Fern 2/Carisma Fern 2 Original.md",
    "Races/Humano/Culture.md",
    "Races/Humano/Lore.md",
    "Characters/Rust/Carisma.md",
    "auverse_vault/to-do.md",
    "auverse_vault/mandamentos.md",
    "auverse_vault/changelog.md",
    "auverse_vault/Races/Arthe/Lore.md",
    "auverse_vault/Races/Arthe/Culture.md",
    "auverse_vault/Parts/Parte 8/Auverse Parte 8.md",
    "auverse_vault/Parts/Parte 1/Auverse Parte 1.md",
    "auverse_vault/Factions/Celestiais/Lore.md",
    "auverse_vault/Factions/Regime de Okahara/Lore.md",
    "auverse_vault/Factions/Caçadores de Recompensas/Lore.md",
    "auverse_vault/Events/Regime de Okahara.md",
    "auverse_vault/Events/Criação do Abismo.md",
    "auverse_vault/Events/Criação do Coliseu.md",
    "auverse_vault/Events/Criação do Universo.md"
  ]
}